cronohub/__init__.py
cronohub/__main__.py
cronohub/cronohub.py
cronohub/source_plugin.py
cronohub/target_plugin.py
cronohub-0.1.2.dist-info/LICENSE.txt
cronohub-0.1.2.dist-info/METADATA
cronohub-0.1.2.dist-info/WHEEL
cronohub-0.1.2.dist-info/entry_points.txt
cronohub-0.1.2.dist-info/top_level.txt
cronohub-0.1.2.dist-info/RECORD
